[
  {
    "Nom": "save1",
    "Sources": "C:\\Users\\bbila\\OneDrive - Association Cesi Viacesi mail\\A3\\prog_systeme\\debut",
    "Cible": "C:\\Users\\bbila\\OneDrive - Association Cesi Viacesi mail\\A3\\prog_systeme\\fin",
    "size": "510",
    "filetransfertime": "00:00:00.0564472",
    "time": "2021-12-01T16:23:36.786717+01:00",
    "chiffrement": null,
    "prio": null,
    "encrypttime": null
  },
  {
    "Nom": "save1",
    "Sources": "C:\\Users\\bbila\\OneDrive - Association Cesi Viacesi mail\\A3\\prog_systeme\\debut",
    "Cible": "C:\\Users\\bbila\\OneDrive - Association Cesi Viacesi mail\\A3\\prog_systeme\\fin",
    "size": "510",
    "filetransfertime": "00:00:00.1313747",
    "time": "2021-12-01T16:26:48.361503+01:00",
    "chiffrement": null,
    "prio": null,
    "encrypttime": null
  },
  {
    "Nom": "save1",
    "Sources": "C:\\Users\\bbila\\OneDrive - Association Cesi Viacesi mail\\A3\\prog_systeme\\debut",
    "Cible": "C:\\Users\\bbila\\OneDrive - Association Cesi Viacesi mail\\A3\\prog_systeme\\fin",
    "size": "510",
    "filetransfertime": "00:00:00.0221555",
    "time": "2021-12-01T16:27:17.490217+01:00",
    "chiffrement": null,
    "prio": null,
    "encrypttime": null
  },
  {
    "Nom": "save1",
    "Sources": "C:\\Users\\bbila\\OneDrive - Association Cesi Viacesi mail\\A3\\prog_systeme\\debut",
    "Cible": "C:\\Users\\bbila\\OneDrive - Association Cesi Viacesi mail\\A3\\prog_systeme\\fin",
    "size": "510",
    "filetransfertime": "00:00:00.0219103",
    "time": "2021-12-01T16:27:38.5926576+01:00",
    "chiffrement": null,
    "prio": null,
    "encrypttime": null
  },
  {
    "Nom": "save1",
    "Sources": "C:\\Users\\bbila\\OneDrive - Association Cesi Viacesi mail\\A3\\prog_systeme\\debut",
    "Cible": "C:\\Users\\bbila\\OneDrive - Association Cesi Viacesi mail\\A3\\prog_systeme\\fin",
    "size": "510",
    "filetransfertime": "00:00:00.0230259",
    "time": "2021-12-01T16:27:54.2407785+01:00",
    "chiffrement": null,
    "prio": null,
    "encrypttime": null
  },
  {
    "Nom": "save1",
    "Sources": "C:\\Users\\bbila\\OneDrive - Association Cesi Viacesi mail\\A3\\prog_systeme\\debut",
    "Cible": "C:\\Users\\bbila\\OneDrive - Association Cesi Viacesi mail\\A3\\prog_systeme\\fin",
    "size": "510",
    "filetransfertime": "00:00:00.0166687",
    "time": "2021-12-01T16:34:56.6834012+01:00",
    "chiffrement": null,
    "prio": null,
    "encrypttime": null
  },
  {
    "Nom": "save2",
    "Sources": "C:\\Users\\bbila\\OneDrive - Association Cesi Viacesi mail\\A3\\stage",
    "Cible": "C:\\Users\\bbila\\OneDrive - Association Cesi Viacesi mail\\A3\\prog_systeme\\fin",
    "size": "141",
    "filetransfertime": "00:00:00.0041673",
    "time": "2021-12-01T16:35:46.5125007+01:00",
    "chiffrement": null,
    "prio": null,
    "encrypttime": null
  },
  {
    "Nom": "save3",
    "Sources": "C:\\Users\\bbila\\OneDrive - Association Cesi Viacesi mail\\A3\\Poppy",
    "Cible": "C:\\Users\\bbila\\OneDrive - Association Cesi Viacesi mail\\A3\\prog_systeme\\fin",
    "size": "306",
    "filetransfertime": "00:00:00.0253262",
    "time": "2021-12-01T16:36:34.9800272+01:00",
    "chiffrement": null,
    "prio": null,
    "encrypttime": null
  },
  {
    "Nom": "save1",
    "Sources": "C:\\Users\\bbila\\OneDrive - Association Cesi Viacesi mail\\A3\\prog_systeme\\debut",
    "Cible": "C:\\Users\\bbila\\OneDrive - Association Cesi Viacesi mail\\A3\\prog_systeme\\fin",
    "size": "510",
    "filetransfertime": "00:00:00.0124340",
    "time": "2021-12-01T16:36:59.0283937+01:00",
    "chiffrement": null,
    "prio": null,
    "encrypttime": null
  },
  {
    "Nom": "save2",
    "Sources": "C:\\Users\\bbila\\OneDrive - Association Cesi Viacesi mail\\A3\\stage",
    "Cible": "C:\\Users\\bbila\\OneDrive - Association Cesi Viacesi mail\\A3\\prog_systeme\\fin",
    "size": "141",
    "filetransfertime": "00:00:00.0040221",
    "time": "2021-12-01T16:37:02.788702+01:00",
    "chiffrement": null,
    "prio": null,
    "encrypttime": null
  },
  {
    "Nom": "save3",
    "Sources": "C:\\Users\\bbila\\OneDrive - Association Cesi Viacesi mail\\A3\\Poppy",
    "Cible": "C:\\Users\\bbila\\OneDrive - Association Cesi Viacesi mail\\A3\\prog_systeme\\fin",
    "size": "306",
    "filetransfertime": "00:00:00.0089026",
    "time": "2021-12-01T16:37:06.844295+01:00",
    "chiffrement": null,
    "prio": null,
    "encrypttime": null
  },
  {
    "Nom": "save1",
    "Sources": "C:\\Users\\bbila\\OneDrive - Association Cesi Viacesi mail\\A3\\prog_systeme\\debut",
    "Cible": "C:\\Users\\bbila\\OneDrive - Association Cesi Viacesi mail\\A3\\prog_systeme\\fin",
    "size": "510",
    "filetransfertime": "00:00:00.0189270",
    "time": "2021-12-01T16:38:28.4319673+01:00",
    "chiffrement": null,
    "prio": null,
    "encrypttime": null
  },
  {
    "Nom": "save2",
    "Sources": "C:\\Users\\bbila\\OneDrive - Association Cesi Viacesi mail\\A3\\stage",
    "Cible": "C:\\Users\\bbila\\OneDrive - Association Cesi Viacesi mail\\A3\\prog_systeme\\fin",
    "size": "141",
    "filetransfertime": "00:00:00.0052132",
    "time": "2021-12-01T16:38:50.7801707+01:00",
    "chiffrement": null,
    "prio": null,
    "encrypttime": null
  },
  {
    "Nom": "save3",
    "Sources": "C:\\Users\\bbila\\OneDrive - Association Cesi Viacesi mail\\A3\\Poppy",
    "Cible": "C:\\Users\\bbila\\OneDrive - Association Cesi Viacesi mail\\A3\\prog_systeme\\fin",
    "size": "306",
    "filetransfertime": "00:00:00.0086550",
    "time": "2021-12-01T16:38:56.2014894+01:00",
    "chiffrement": null,
    "prio": null,
    "encrypttime": null
  },
  {
    "Nom": "save1",
    "Sources": "C:\\Users\\bbila\\OneDrive - Association Cesi Viacesi mail\\A3\\prog_systeme\\debut",
    "Cible": "C:\\Users\\bbila\\OneDrive - Association Cesi Viacesi mail\\A3\\prog_systeme\\fin",
    "size": "510",
    "filetransfertime": "00:00:00.0246690",
    "time": "2021-12-03T09:31:51.7099344+01:00",
    "chiffrement": null,
    "prio": null,
    "encrypttime": null
  },
  {
    "Nom": "save2",
    "Sources": "C:\\Users\\bbila\\OneDrive - Association Cesi Viacesi mail\\A3\\stage",
    "Cible": "C:\\Users\\bbila\\OneDrive - Association Cesi Viacesi mail\\A3\\prog_systeme\\fin",
    "size": "141",
    "filetransfertime": "00:00:00.0031187",
    "time": "2021-12-03T09:32:02.4003916+01:00",
    "chiffrement": null,
    "prio": null,
    "encrypttime": null
  },
  {
    "Nom": "save3",
    "Sources": "C:\\Users\\bbila\\OneDrive - Association Cesi Viacesi mail\\A3\\Poppy",
    "Cible": "C:\\Users\\bbila\\OneDrive - Association Cesi Viacesi mail\\A3\\prog_systeme\\fin",
    "size": "306",
    "filetransfertime": "00:00:00.0234843",
    "time": "2021-12-03T09:32:05.4092088+01:00",
    "chiffrement": null,
    "prio": null,
    "encrypttime": null
  },
  {
    "Nom": "save1",
    "Sources": "C:\\Users\\bbila\\OneDrive - Association Cesi Viacesi mail\\A3\\prog_systeme\\debut",
    "Cible": "C:\\Users\\bbila\\OneDrive - Association Cesi Viacesi mail\\A3\\prog_systeme\\fin",
    "size": "510",
    "filetransfertime": "00:00:00.3339664",
    "time": "2021-12-03T14:24:51.2229763+01:00",
    "chiffrement": null,
    "prio": null,
    "encrypttime": null
  },
  {
    "Nom": "save1",
    "Sources": "C:\\Users\\bbila\\OneDrive - Association Cesi Viacesi mail\\A3\\prog_systeme\\debut",
    "Cible": "C:\\Users\\bbila\\OneDrive - Association Cesi Viacesi mail\\A3\\prog_systeme\\fin",
    "size": "510",
    "filetransfertime": "00:00:00.4646696",
    "time": "2021-12-03T14:26:18.4807072+01:00",
    "chiffrement": null,
    "prio": null,
    "encrypttime": null
  },
  {
    "Nom": "save1",
    "Sources": "C:\\Users\\bbila\\OneDrive - Association Cesi Viacesi mail\\A3\\prog_systeme\\debut",
    "Cible": "C:\\Users\\bbila\\OneDrive - Association Cesi Viacesi mail\\A3\\prog_systeme\\fin",
    "size": "510",
    "filetransfertime": "00:00:00.3635490",
    "time": "2021-12-03T14:33:28.0465502+01:00",
    "chiffrement": null,
    "prio": null,
    "encrypttime": null
  },
  {
    "Nom": "save1",
    "Sources": "C:\\debut",
    "Cible": "C:\\fin",
    "size": "165",
    "filetransfertime": "00:00:00.1888626",
    "time": "2021-12-03T14:53:57.057535+01:00",
    "chiffrement": null,
    "prio": null,
    "encrypttime": null
  },
  {
    "Nom": "save1",
    "Sources": "C:\\debut",
    "Cible": "C:\\fin",
    "size": "165",
    "filetransfertime": "00:00:00.0249343",
    "time": "2021-12-03T15:00:27.2846303+01:00",
    "chiffrement": null,
    "prio": null,
    "encrypttime": null
  },
  {
    "Nom": "save1",
    "Sources": "C:\\debut",
    "Cible": "C:\\fin",
    "size": "165",
    "filetransfertime": "00:00:00.2797160",
    "time": "2021-12-03T15:01:42.7214537+01:00",
    "chiffrement": null,
    "prio": null,
    "encrypttime": null
  },
  {
    "Nom": "save1",
    "Sources": "C:\\debut",
    "Cible": "C:\\fin",
    "size": "165",
    "filetransfertime": "00:00:00.2474798",
    "time": "2021-12-03T15:02:55.9053223+01:00",
    "chiffrement": null,
    "prio": null,
    "encrypttime": null
  },
  {
    "Nom": "save1",
    "Sources": "C:\\debut",
    "Cible": "C:\\fin",
    "size": "165",
    "filetransfertime": "00:00:00.1970888",
    "time": "2021-12-03T15:06:26.5658317+01:00",
    "chiffrement": null,
    "prio": null,
    "encrypttime": null
  },
  {
    "Nom": "save1",
    "Sources": "C:\\debut",
    "Cible": "C:\\fin",
    "size": "165",
    "filetransfertime": "00:00:00.1219817",
    "time": "2021-12-03T15:15:51.9794154+01:00",
    "chiffrement": null,
    "prio": null,
    "encrypttime": null
  },
  {
    "Nom": "save1",
    "Sources": "C:\\debut",
    "Cible": "C:\\fin",
    "size": "165",
    "filetransfertime": "00:00:00.1273854",
    "time": "2021-12-03T15:17:08.3739456+01:00",
    "chiffrement": null,
    "prio": null,
    "encrypttime": null
  },
  {
    "Nom": "save1",
    "Sources": "C:\\debut",
    "Cible": "C:\\fin",
    "size": "165",
    "filetransfertime": "00:00:00.0158578",
    "time": "2021-12-03T15:19:12.4563212+01:00",
    "chiffrement": null,
    "prio": null,
    "encrypttime": null
  },
  {
    "Nom": "save1",
    "Sources": "C:\\debut",
    "Cible": "C:\\fin",
    "size": "165",
    "filetransfertime": "00:00:00.1332908",
    "time": "2021-12-03T15:21:08.7120992+01:00",
    "chiffrement": null,
    "prio": null,
    "encrypttime": null
  },
  {
    "Nom": "save1",
    "Sources": "C:\\debut",
    "Cible": "C:\\fin",
    "size": "165",
    "filetransfertime": "00:00:00.0156511",
    "time": "2021-12-03T15:22:09.6883285+01:00",
    "chiffrement": null,
    "prio": null,
    "encrypttime": null
  },
  {
    "Nom": "save1",
    "Sources": "C:\\debut",
    "Cible": "C:\\fin",
    "size": "165",
    "filetransfertime": "00:00:00.1212446",
    "time": "2021-12-03T15:23:16.537097+01:00",
    "chiffrement": null,
    "prio": null,
    "encrypttime": null
  },
  {
    "Nom": "save1",
    "Sources": "C:\\debut",
    "Cible": "C:\\fin",
    "size": "165",
    "filetransfertime": "00:00:00.0149645",
    "time": "2021-12-03T15:25:02.8233241+01:00",
    "chiffrement": null,
    "prio": null,
    "encrypttime": null
  },
  {
    "Nom": "save1",
    "Sources": "C:\\debut",
    "Cible": "C:\\fin",
    "size": "165",
    "filetransfertime": "00:00:10.8202744",
    "time": "2021-12-03T15:26:30.4063208+01:00",
    "chiffrement": null,
    "prio": null,
    "encrypttime": null
  },
  {
    "Nom": "save1",
    "Sources": "C:\\debut",
    "Cible": "C:\\fin",
    "size": "165",
    "filetransfertime": "00:00:02.3002066",
    "time": "2021-12-03T15:28:11.2555873+01:00",
    "chiffrement": null,
    "prio": null,
    "encrypttime": null
  },
  {
    "Nom": "save1",
    "Sources": "C:\\debut",
    "Cible": "C:\\fin",
    "size": "165",
    "filetransfertime": "00:00:05.0608591",
    "time": "2021-12-03T15:29:38.1507038+01:00",
    "chiffrement": null,
    "prio": null,
    "encrypttime": null
  },
  {
    "Nom": "save1",
    "Sources": "C:\\debut",
    "Cible": "C:\\fin",
    "size": "165",
    "filetransfertime": "00:00:00.0001406",
    "time": "2021-12-03T15:34:05.9544665+01:00",
    "chiffrement": null,
    "prio": null,
    "encrypttime": null
  },
  {
    "Nom": "save1",
    "Sources": "C:\\debut",
    "Cible": "C:\\fin",
    "size": "165",
    "filetransfertime": "00:00:00.0001826",
    "time": "2021-12-03T15:35:36.0266755+01:00",
    "chiffrement": null,
    "prio": null,
    "encrypttime": null
  },
  {
    "Nom": "save1",
    "Sources": "C:\\debut",
    "Cible": "C:\\fin",
    "size": "165",
    "filetransfertime": "00:00:00.0001542",
    "time": "2021-12-03T15:36:53.8071772+01:00",
    "chiffrement": null,
    "prio": null,
    "encrypttime": null
  },
  {
    "Nom": "save1",
    "Sources": "C:\\debut",
    "Cible": "C:\\fin",
    "size": "165",
    "filetransfertime": "00:00:00.0001557",
    "time": "2021-12-03T15:39:15.3506428+01:00",
    "chiffrement": null,
    "prio": null,
    "encrypttime": null
  },
  {
    "Nom": "save1",
    "Sources": "C:\\debut",
    "Cible": "C:\\fin",
    "size": "165",
    "filetransfertime": "00:00:00.0001627",
    "time": "2021-12-03T19:57:23.1582332+01:00",
    "chiffrement": null,
    "prio": null,
    "encrypttime": null
  },
  {
    "Nom": "save1",
    "Sources": "C:\\debut",
    "Cible": "C:\\fin",
    "size": "165",
    "filetransfertime": "00:00:00.0001422",
    "time": "2021-12-14T16:14:30.0939567+01:00",
    "chiffrement": null,
    "prio": null,
    "encrypttime": null
  },
  {
    "Nom": "save4",
    "Sources": "C:\\debut",
    "Cible": "C:\\fin",
    "size": "165",
    "filetransfertime": "00:00:00.0001167",
    "time": "2021-12-15T11:07:34.9031885+01:00",
    "chiffrement": "*.txt",
    "prio": ".pdf",
    "encrypttime": "0"
  },
  {
    "Nom": "save1",
    "Sources": "C:\\debut",
    "Cible": "C:\\fin",
    "size": "165",
    "filetransfertime": "00:00:00.0001593",
    "time": "2021-12-15T11:35:12.3131678+01:00",
    "chiffrement": "*.txt",
    "prio": ".txt",
    "encrypttime": "0"
  },
  {
    "Nom": "save1",
    "Sources": "C:\\debut",
    "Cible": "C:\\fin",
    "size": "165",
    "filetransfertime": "00:00:00.0001317",
    "time": "2021-12-15T11:36:11.9886495+01:00",
    "chiffrement": "*.txt",
    "prio": ".txt",
    "encrypttime": "0"
  },
  {
    "Nom": "save1",
    "Sources": "C:\\debut",
    "Cible": "C:\\fin",
    "size": "165",
    "filetransfertime": "00:00:00.0001382",
    "time": "2021-12-15T11:37:47.0201046+01:00",
    "chiffrement": "*.txt",
    "prio": ".txt",
    "encrypttime": "0"
  },
  {
    "Nom": "save1",
    "Sources": "C:\\debut",
    "Cible": "C:\\fin",
    "size": "165",
    "filetransfertime": "00:00:00.0000927",
    "time": "2021-12-15T11:38:19.2781675+01:00",
    "chiffrement": "*.txt",
    "prio": ".txt",
    "encrypttime": "0"
  },
  {
    "Nom": "save1",
    "Sources": "C:\\debut",
    "Cible": "C:\\fin",
    "size": "165",
    "filetransfertime": "00:00:00.0001614",
    "time": "2021-12-15T11:39:53.9829817+01:00",
    "chiffrement": "*.txt",
    "prio": ".txt",
    "encrypttime": "0"
  },
  {
    "Nom": "save1",
    "Sources": "C:\\debut",
    "Cible": "C:\\fin",
    "size": "165",
    "filetransfertime": "00:00:00.0001224",
    "time": "2021-12-15T11:43:30.6613686+01:00",
    "chiffrement": "*.txt",
    "prio": ".txt",
    "encrypttime": "0"
  },
  {
    "Nom": "save1",
    "Sources": "C:\\debut",
    "Cible": "C:\\fin",
    "size": "165",
    "filetransfertime": "00:00:00.0001396",
    "time": "2021-12-15T11:44:06.427731+01:00",
    "chiffrement": "*.txt",
    "prio": ".txt",
    "encrypttime": "0"
  },
  {
    "Nom": "save1",
    "Sources": "C:\\debut",
    "Cible": "C:\\fin",
    "size": "165",
    "filetransfertime": "00:00:00.0000966",
    "time": "2021-12-15T11:45:10.3560835+01:00",
    "chiffrement": "*.txt *.pdf",
    "prio": ".txt",
    "encrypttime": "0"
  },
  {
    "Nom": "save1",
    "Sources": "C:\\debut",
    "Cible": "C:\\fin",
    "size": "165",
    "filetransfertime": "00:00:00.0001322",
    "time": "2021-12-15T15:12:44.0276219+01:00",
    "chiffrement": "*.txt *.pdf",
    "prio": ".txt",
    "encrypttime": "0"
  },
  {
    "Nom": "save1",
    "Sources": "C:\\debut",
    "Cible": "C:\\fin",
    "size": "165",
    "filetransfertime": "00:00:00.0001226",
    "time": "2021-12-15T15:38:06.4987233+01:00",
    "chiffrement": "*.txt *.pdf",
    "prio": ".txt",
    "encrypttime": "0"
  },
  {
    "Nom": "save1",
    "Sources": "C:\\debut",
    "Cible": "C:\\fin",
    "size": "165",
    "filetransfertime": "00:00:00.0001301",
    "time": "2021-12-15T15:39:41.097327+01:00",
    "chiffrement": "*.txt *.pdf",
    "prio": ".txt",
    "encrypttime": "0"
  },
  {
    "Nom": "save1",
    "Sources": "C:\\debut",
    "Cible": "C:\\fin",
    "size": "165",
    "filetransfertime": "00:00:00.0000758",
    "time": "2021-12-15T15:44:46.1587522+01:00",
    "chiffrement": "*.txt *.pdf",
    "prio": ".txt",
    "encrypttime": "0"
  },
  {
    "Nom": "save1",
    "Sources": "C:\\debut",
    "Cible": "C:\\fin",
    "size": "165",
    "filetransfertime": "00:00:00.0000929",
    "time": "2021-12-15T15:45:39.2456854+01:00",
    "chiffrement": "*.txt *.pdf",
    "prio": ".txt",
    "encrypttime": "0"
  },
  {
    "Nom": "save1",
    "Sources": "C:\\debut",
    "Cible": "C:\\fin",
    "size": "165",
    "filetransfertime": "00:00:00.0000840",
    "time": "2021-12-15T15:46:25.7131892+01:00",
    "chiffrement": "*.txt *.pdf",
    "prio": ".txt",
    "encrypttime": "0"
  },
  {
    "Nom": "save1",
    "Sources": "C:\\debut",
    "Cible": "C:\\fin",
    "size": "165",
    "filetransfertime": "00:00:00.0000799",
    "time": "2021-12-15T15:48:17.4541404+01:00",
    "chiffrement": "*.txt *.pdf",
    "prio": ".txt",
    "encrypttime": "0"
  },
  {
    "Nom": "save1",
    "Sources": "C:\\debut",
    "Cible": "C:\\fin",
    "size": "165",
    "filetransfertime": "00:00:00.0000919",
    "time": "2021-12-15T16:46:23.258442+01:00",
    "chiffrement": "*.txt *.pdf",
    "prio": ".txt",
    "encrypttime": "0"
  },
  {
    "Nom": "save1",
    "Sources": "C:\\debut",
    "Cible": "C:\\fin",
    "size": "165",
    "filetransfertime": "00:00:00.0000777",
    "time": "2021-12-15T16:48:20.4481606+01:00",
    "chiffrement": "*.txt *.pdf",
    "prio": ".txt",
    "encrypttime": "0"
  },
  {
    "Nom": "save1",
    "Sources": "C:\\debut",
    "Cible": "C:\\fin",
    "size": "165",
    "filetransfertime": "00:00:00.0000805",
    "time": "2021-12-15T16:50:54.9093839+01:00",
    "chiffrement": "*.txt *.pdf",
    "prio": ".txt",
    "encrypttime": "0"
  },
  {
    "Nom": "save1",
    "Sources": "C:\\debut",
    "Cible": "C:\\fin",
    "size": "165",
    "filetransfertime": "00:00:00.0000831",
    "time": "2021-12-15T16:51:13.5196918+01:00",
    "chiffrement": "*.txt *.pdf",
    "prio": ".txt",
    "encrypttime": "0"
  },
  {
    "Nom": "save1",
    "Sources": "C:\\debut",
    "Cible": "C:\\fin",
    "size": "165",
    "filetransfertime": "00:00:00.0064064",
    "time": "2021-12-15T16:54:05.460474+01:00",
    "chiffrement": "*.txt *.pdf",
    "prio": ".txt",
    "encrypttime": "0"
  },
  {
    "Nom": "save1",
    "Sources": "C:\\debut",
    "Cible": "C:\\fin",
    "size": "165",
    "filetransfertime": "00:00:00.0001391",
    "time": "2021-12-15T16:54:59.7587582+01:00",
    "chiffrement": "*.txt *.pdf",
    "prio": ".txt",
    "encrypttime": "0"
  },
  {
    "Nom": "save1",
    "Sources": "C:\\debut",
    "Cible": "C:\\fin",
    "size": "165",
    "filetransfertime": "00:00:00.0001316",
    "time": "2021-12-15T16:57:54.4200321+01:00",
    "chiffrement": "*.txt *.pdf",
    "prio": ".txt",
    "encrypttime": "0"
  },
  {
    "Nom": "save1",
    "Sources": "C:\\debut",
    "Cible": "C:\\fin",
    "size": "165",
    "filetransfertime": "00:00:00.0001267",
    "time": "2021-12-15T17:01:04.2877284+01:00",
    "chiffrement": "*.txt *.pdf",
    "prio": ".txt",
    "encrypttime": "0"
  }
]